Metadata-Version: 2.1
Name: Mentoss
Version: 0.0.3
Summary: Square and Cube any real number
Home-page: https://github.com/Eloyjaws/Mentoss
Author: Eniola Ajiboye
Author-email: eajiboye@andrew.cmu.edu
License: UNKNOWN
Platform: UNKNOWN
Classifier: Programming Language :: Python :: 3
Classifier: License :: OSI Approved :: MIT License
Classifier: Operating System :: OS Independent
